accounts_generator/__init__.py
accounts_generator/account_generator.py
accounts_generator/check_availability.py
accounts_generator/chrome_driver.py
accounts_generator/fake_account_data.py
accounts_generator/instagram_account_generator.py
accounts_generator/outlook_account_generator.py
accounts_generator/proxy_generator.py
accounts_generator/search_mails.py
accounts_generator/user_agent_handler.py
accounts_generator-0.1.0.dist-info/LICENSE
accounts_generator-0.1.0.dist-info/METADATA
accounts_generator-0.1.0.dist-info/WHEEL
accounts_generator-0.1.0.dist-info/top_level.txt
accounts_generator-0.1.0.dist-info/RECORD
