Metadata-Version: 2.1
Name: accounts-generator
Version: 0.1.0
Summary: Account Generator with Browser Automation
Author-email: Shubham Garg <shubham.garg21@outlook.com>
License: GNU GENERAL PUBLIC LICENSE
Project-URL: homepage, https://github.com/shubhamgarg21/accounts-generator
Project-URL: repository, https://github.com/shubhamgarg21/accounts-generator
Project-URL: documentation, https://github.com/shubhamgarg21/accounts-generator
Keywords: automation
Classifier: Programming Language :: Python :: 3
Classifier: License :: OSI Approved :: GNU General Public License v3 (GPLv3)
Classifier: Operating System :: OS Independent
License-File: LICENSE
Requires-Dist: selenium
Requires-Dist: playwright
Requires-Dist: requests
Requires-Dist: selenium-stealth
Requires-Dist: random-password-generator
Requires-Dist: Faker
Requires-Dist: lxml
Requires-Dist: fake-headers
Requires-Dist: pillow
